orbis_addon_satyanweshi/__init__.py
orbis_addon_satyanweshi/description.txt
orbis_addon_satyanweshi/main.py
orbis_addon_satyanweshi/templates.py
orbis_addon_satyanweshi-2.1.1.dist-info/LICENSE
orbis_addon_satyanweshi-2.1.1.dist-info/METADATA
orbis_addon_satyanweshi-2.1.1.dist-info/WHEEL
orbis_addon_satyanweshi-2.1.1.dist-info/top_level.txt
orbis_addon_satyanweshi-2.1.1.dist-info/RECORD
