Metadata-Version: 2.1
Name: orbis-addon-satyanweshi
Version: 2.1.1
Summary: The Satyanweshi Addon for Orbis to compare two evaluation runs with each other.
Home-page: https://github.com/orbis-eval/orbis_addon_satyanweshi
Author: fabod
License: GPL2
Platform: UNKNOWN
Requires-Python: >3.6
Requires-Dist: palettable (==3.1.1)
